[
    {
        "message": "PERSONA",
        "persona-choice": "persona2"
    },
    {
        "message": "CLEAR"
    },
    {
        "message": "Welcome to PTSDialogue"
    },
    {
        "message": "Nice to meet you 😊"
    },
    {
        "message": "I will support your journey to self-manage PTSD. For example, I can help you to: <ul> <li>understand PTSD symptoms</li><li>help you come up with strategies for managing symptoms, and</li><li>assist you to make positive and lasting changes in your life</li></ul>"
    },
    {
        "message": "Is the time for you to begin?",
        "options": ["Yes", "No"],
        "dialogue": ["start-conversation.json","end-conversation.json"]
    }
]